bouldern/__init__.py
bouldern-0.0.3.dist-info/METADATA
bouldern-0.0.3.dist-info/WHEEL
bouldern-0.0.3.dist-info/top_level.txt
bouldern-0.0.3.dist-info/RECORD
