Metadata-Version: 2.1
Name: bouldern
Version: 0.0.3
Summary: Module for fun, you can contact me, if you need the package name.
Home-page: UNKNOWN
Author: Marius Huerzeler
Author-email: huerzeler.marius@gmail.com
License: MIT
Platform: UNKNOWN
Classifier: Development Status :: 4 - Beta
Classifier: License :: OSI Approved :: MIT License
Classifier: Programming Language :: Python :: 3
Classifier: Programming Language :: Python :: 3.2
Classifier: Programming Language :: Python :: 3.3
Classifier: Programming Language :: Python :: 3.4
Classifier: Programming Language :: Python :: 3.5
Classifier: Programming Language :: Python :: 3.6
Classifier: Programming Language :: Python :: 3.7
Requires-Python: >=3
